biorange/__init__.py
biorange/component/__init__.py
biorange/component/tcmsp_component.py
biorange/data/9606.protein_chemical.links.transfer.v5.0.tsv.gz
biorange/data/GeneCards-SearchResults.csv
biorange/data/TCMSP_NGM_STITCH_INCHIKEY.tsv.gz
biorange/data/TCMSP_mol.csv
biorange/data/TCMSP_tar.csv
biorange/data/TCM_NGM_ISOMERIC_SMILES.csv
biorange/data/TCM_NGM__ADMET.csv
biorange/data/TCM_NGM_inchikey_isosmmieles_11414.csv
biorange/data/TTD_combinez_data.csv
biorange/data/admet_complete_info.csv
biorange/data/admet_filtered_ingredients.csv
biorange/data/config-dock.yaml
biorange/data/config.yaml
biorange/data/first_input_data.csv
biorange/data/inchikey.csv
biorange/data/morbidmap.txt
biorange/data/node_file.csv
biorange/data/node_file333.csv
biorange/data/shared targets of drugs and diseases.csv
biorange/data/shared targets.csv
biorange/data/smiles.csv
biorange/data/type_file.csv
biorange/data/中药NGM_combined_ingredients_inchikey_smiles.csv
biorange/dock/READEME.md
biorange/dock/__init__.py
biorange/dock/dock_plot.py
biorange/dock/dock_run_autodock.py
biorange/dock/dock_run_diffdock.py
biorange/dock/dock_score.py
biorange/dock/smina.py
biorange/dock/smina.static
biorange/dock/todo/6w70.pdb
biorange/dock/todo/6w70_ligand.sdf
biorange/dock/todo/dock_run_smina_need_conda.py
biorange/dock/todo/rank1.sdf
biorange/dock/todo/分子对接-本地smina.ipynb
biorange/enrich_analysis/__init__.py
biorange/enrich_analysis/enrich_gokegg.py
biorange/enrich_analysis/gokegg_4divided.py
biorange/enrich_analysis/plot_bar_gokegg.py
biorange/logger/__init__.py
biorange/logger/logging_config.py
biorange/logger/logging_config.yaml
biorange/ppi/__init__.py
biorange/ppi/generate_type_file.py
biorange/ppi/ppi_final.py
biorange/ppi/ppi_plot.py
biorange/target_predict/__init__.py
biorange/target_predict/data_processing/__init__.py
biorange/target_predict/data_processing/admet.ipynb
biorange/target_predict/data_processing/admet_filtered_ingredients.csv
biorange-1.3.0.dist-info/METADATA
biorange-1.3.0.dist-info/WHEEL
biorange-1.3.0.dist-info/entry_points.txt
biorange-1.3.0.dist-info/RECORD
