Metadata-Version: 2.1
Name: biorange
Version: 1.3.0
Summary: 
Author: liuyan
Author-email: lyfx99@icloud.com
Requires-Python: >=3.10,<4.0
Classifier: Programming Language :: Python :: 3
Classifier: Programming Language :: Python :: 3.10
Classifier: Programming Language :: Python :: 3.11
Classifier: Programming Language :: Python :: 3.12
Requires-Dist: bioblend (>=1.3.0,<2.0.0)
Requires-Dist: bs4 (>=0.0.2,<0.0.3)
Requires-Dist: docker (>=7.1.0,<8.0.0)
Requires-Dist: gseapy (>=1.1.3,<2.0.0)
Requires-Dist: matplotlib (>=3.9.2,<4.0.0)
Requires-Dist: matplotlib-venn (>=1.1.1,<2.0.0)
Requires-Dist: mygene (>=3.2.2,<4.0.0)
Requires-Dist: networkx (>=3.3,<4.0)
Requires-Dist: pandas (>=2.2.2,<3.0.0)
Requires-Dist: planemo (>=0.75.26,<0.76.0)
Requires-Dist: playwright (>=1.46.0,<2.0.0)
Requires-Dist: plotnine (>=0.13.6,<0.14.0)
Requires-Dist: py3dmol (>=2.4.0,<3.0.0)
Requires-Dist: pytest (>=8.3.3,<9.0.0)
Requires-Dist: pyyaml (>=6.0.2,<7.0.0)
Requires-Dist: requests (>=2.32.3,<3.0.0)
